<OverlayData>
    <MarkerCategory name="leag" DisplayName="Lady Elyssa's AP Guides" mapDisplaySize="16">
        
        <MarkerCategory name="voe" DisplayName="Visions of Eternity">
        
            <MarkerCategory name="story" DisplayName="Story Achievements" fadeNear="1600" fadeFar="3000">
                
                <MarkerCategory name="prologue" IsSeparator="1" DisplayName="PROLOGUE: On the Sly"/>
                <MarkerCategory name="ledger" DisplayName="Lionguard Ledger" achievementId="8979" iconFile="Data/Images/Icons/Orb - Green - S.png" maxSize="16"/>
                <MarkerCategory name="out" DisplayName="And Stay Out!" achievementId="9068" texture="Data/Images/Trails/Dashed Lines - Fine with Shadow.png" color="00FF00" animSpeed="0"/>

                <MarkerCategory name="ch1" IsSeparator="1" DisplayName="CHAPTER 1: Unscheduled Departures"/>
                <MarkerCategory name="ledger" DisplayName="Lionguard Ledger" achievementId="8979" iconFile="Data/Images/Icons/Orb - Green - S.png" maxSize="16"/>
                <MarkerCategory name="divination" DisplayName="Nautical Divination" achievementId="8970">
                     <MarkerCategory name="left" DisplayName="Left" iconFile="Data/Images/Icons/Direction - Left.png" maxSize="32"/>
                     <MarkerCategory name="right" DisplayName="Right" iconFile="Data/Images/Icons/Direction - Right.png" maxSize="32"/>
                     <MarkerCategory name="straight" DisplayName="Straight" iconFile="Data/Images/Icons/Direction - Straight.png" maxSize="32"/>
                </MarkerCategory>
                
                <MarkerCategory name="ch2" IsSeparator="1" DisplayName="CHAPTER 2: Solid Ground"/>
                <MarkerCategory name="cultural" DisplayName="Cultural Exchange" achievementId="8925">
                    <MarkerCategory name="ley" DisplayName="Ley Lines for the Layman" iconFile="Data/Images/Icons/Tattered Journal.png" inGameVisibility="0" mapDisplaySize="32"/>
                    <MarkerCategory name="intel" DisplayName="Intel Report" iconFile="Data/Images/Icons/Tattered Journal.png" inGameVisibility="0" mapDisplaySize="32"/>
                    <MarkerCategory name="kestrel" DisplayName="Kestrel Journal" iconFile="Data/Images/Icons/Tattered Journal.png" inGameVisibility="0" mapDisplaySize="32"/>
                    <MarkerCategory name="hunter" DisplayName="Hunter's Journal" iconFile="Data/Images/Icons/Tattered Journal.png" inGameVisibility="0" mapDisplaySize="32"/>
                    <MarkerCategory name="nautical" DisplayName="Nautical Charts" iconFile="Data/Images/Icons/Tattered Journal.png" inGameVisibility="0" mapDisplaySize="32"/>
                </MarkerCategory>

                <MarkerCategory name="beautiful" DisplayName="It's So Beautiful" achievementId="8985" iconFile="Data/Images/Emote - Cry.png" maxSize="64" mapVisibility="0" miniMapVisibility="0"/>
                
                <MarkerCategory name="zeba" DisplayName="Zeba Deserves Better" achievementId="9080" iconFile="Data/Images/Icons/Orb - Green - S.png" maxSize="16" heightOffset="-0.25"/>
                
                <MarkerCategory name="wavehawks" DisplayName="Wavehawks Are My Passion" achievementId="8978" iconFile="Data/Images/Icons/Talk.png" maxSize="24" mapDisplaySize="48"/>
                
                <MarkerCategory name="fundamentals" DisplayName="Wavehawks Fundamentals" achievementId="8990">
                    <MarkerCategory name="tooth" DisplayName="Predator's Tooth" iconFile="Data/Images/Icons/Predator's Tooth.png" inGameVisibility="0" mapDisplaySize="32"/>
                    <MarkerCategory name="treats" DisplayName="Skimmer Treats" iconFile="Data/Images/Icons/Extra Fresh Fish.png" inGameVisibility="0" mapDisplaySize="32"/>
                    <MarkerCategory name="package" DisplayName="Lost Package" iconFile="Data/Images/Icons/Wavehawk Package.png" inGameVisibility="0" mapDisplaySize="32"/>
                    <MarkerCategory name="net" DisplayName="Fishing Net" iconFile="Data/Images/Icons/Fishing Net.png" inGameVisibility="0" mapDisplaySize="32"/>
                    <MarkerCategory name="toy" DisplayName="Wavehawk Toy" iconFile="Data/Images/Icons/Wavehawk Toy.png" inGameVisibility="0" mapDisplaySize="32"/>
                    <MarkerCategory name="token" DisplayName="Token of Affection" iconFile="Data/Images/Icons/Token of Affection.png" inGameVisibility="0" mapDisplaySize="32"/>
                </MarkerCategory>

                <MarkerCategory name="ch3" IsSeparator="1" DisplayName="CHAPTER 3: Eyes, Ears, and Arms"/>
                <MarkerCategory name="flawless" DisplayName="Flawless Hacker" achievementId="8944" iconFile="Data/Images/Icons/Orb - Red - S.png" maxSize="16" heightOffset="-0.5"/>
                <MarkerCategory name="enemy" DisplayName="The Enemy of My Enemy Is Still My Enemy" achievementId="8896" iconFile="Data/Images/Icons/Talk.png" minSize="16" maxSize="24" heightOffset="-0.5"/>
                <MarkerCategory name="overindulgence" DisplayName="Overindulgence" achievementId="8949" iconFile="Data/Images/Icons/Talk.png" maxSize="16" heightOffset="-0.5"/>
                
                <MarkerCategory name="ch4" IsSeparator="1" DisplayName="CHAPTER 4: Truths Unearthed"/>
                <MarkerCategory name="beatem" DisplayName="If You Can't Beat 'Em" achievementId="9075" iconFile="Data/Images/Emote - Dance.png" maxSize="16" heightOffset="-0.5"/>
                <MarkerCategory name="swift" DisplayName="Swift Skimming" achievementId="9079" iconFile="Data/Images/Icons/Targeted Object - Green.png" maxSize="32" heightOffset="-0.2">
                    <MarkerCategory name="trail" DisplayName="Trail"/>
                </MarkerCategory>
                
                <MarkerCategory name="ch5" IsSeparator="1" DisplayName="CHAPTER 5: Beneath the Canopy"/>
                <MarkerCategory name="agents" DisplayName="Track down scouts around Foothold Bivouac" achievementId="9017">
                    <MarkerCategory name="vigil" DisplayName="Vigil Scout Premhoc" iconFile="Data/Images/Circle - Green.png" inGameVisibility="0" mapDisplaySize="40"/>
                    <MarkerCategory name="kestrel" DisplayName="Kestrel Choole" iconFile="Data/Images/Circle - Green.png" inGameVisibility="0" mapDisplaySize="40"/>
                    <MarkerCategory name="scout" DisplayName="Scout Yakuti" iconFile="Data/Images/Circle - Green.png" inGameVisibility="0" mapDisplaySize="40"/>
                    <MarkerCategory name="ward" DisplayName="Astral Ward Scout Trima" iconFile="Data/Images/Circle - Green.png" inGameVisibility="0" mapDisplaySize="40"/>
                </MarkerCategory>
                
                <MarkerCategory name="ch6" IsSeparator="1" DisplayName="CHAPTER 6: Ruins of the Old World"/>
                
                <MarkerCategory name="digging" DisplayName="Digging for Knowledge" achievementId="8988">
                    <MarkerCategory name="icon" DisplayName="Toggle Icon" iconFile="Data/Images/Icons/Collections - Green.png" inGameVisibility="0" mapDisplaySize="40"/>
                    <MarkerCategory name="trail" DisplayName="Toggle Trail"/>
                </MarkerCategory>
                
                <MarkerCategory name="ch7" IsSeparator="1" DisplayName="CHAPTER 7: Fumbling in the Dark"/>
                <MarkerCategory name="mistakes" DisplayName="A Journal of Mistakes" achievementId="9005" iconFile="Data/Images/Icons/Orb - Yellow - S.png" maxSize="16" heightOffset="-0.25" mapDisplaySize="32"/>

                <MarkerCategory name="ch8" IsSeparator="1" DisplayName="CHAPTER 8: Path of Divinity"/>
                <MarkerCategory name="creation" DisplayName="A Fresh Start on Life" achievementId="8948" iconFile="Data/Images/A Fresh Start on Life.png" mapDisplaySize="96" inGameVisibility="0"/>
                <MarkerCategory name="doorstep" DisplayName="The Doorstep of Divinity" achievementId="8946">
                    <MarkerCategory name="set" IsSeparator="1" DisplayName="SETTINGS"/>
                    <MarkerCategory name="wp" DisplayName="Toggle Waypoint Markers" iconFile="Data/Images/Icons/Blank.png" triggerrange="5" autotrigger="true"/>
                    <MarkerCategory name="mount" DisplayName="Mounts" miniMapVisibility="0" minSize="24" maxSize="32">
                        <MarkerCategory name="skimmer" DisplayName="Skimmer" iconFile="Data/Images/Mounts/Mount_Skimmer.png"/>
                        <MarkerCategory name="skyscale" DisplayName="Skyscale" iconFile="Data/Images/Mounts/Mount_Skyscale.png"/>
                        <MarkerCategory name="springer" DisplayName="Springer" iconFile="Data/Images/Mounts/Mount_Springer.png"/>
                    </MarkerCategory>
                    <MarkerCategory name="numbers" DisplayName="Trail Number">
                        <MarkerCategory name="1" DisplayName="One" iconFile="Data/Images/Numbers/1.png" miniMapVisibility="0" minSize="16" maxSize="24"/>
                        <MarkerCategory name="2" DisplayName="Two" iconFile="Data/Images/Numbers/2.png" miniMapVisibility="0" minSize="16" maxSize="24"/>
                        <MarkerCategory name="3" DisplayName="Three" iconFile="Data/Images/Numbers/3.png" miniMapVisibility="0" minSize="16" maxSize="24"/>
                        <MarkerCategory name="4" DisplayName="Four" iconFile="Data/Images/Numbers/4.png" miniMapVisibility="0" minSize="16" maxSize="24"/>
                        <MarkerCategory name="5" DisplayName="Five" iconFile="Data/Images/Numbers/5.png" miniMapVisibility="0" minSize="16" maxSize="24"/>
                        <MarkerCategory name="6" DisplayName="Six" iconFile="Data/Images/Numbers/6.png" miniMapVisibility="0" minSize="16" maxSize="24"/>
                    </MarkerCategory>
                    <MarkerCategory name="collectible" IsSeparator="1" DisplayName="COLLECTIBLES"/>
                    <MarkerCategory name="sample" DisplayName="Castoran Magic Sample"  iconFile="Data/Images/Icons/Collections - Green.png" inGameVisibility="0" mapDisplaySize="40"/>
                    <MarkerCategory name="shard" DisplayName="Inert Shadowstone Shard"  iconFile="Data/Images/Icons/Collections - Green.png" inGameVisibility="0" mapDisplaySize="40"/>
                    <MarkerCategory name="asrsketch" DisplayName="Arcane Spell Rune Sketch"  iconFile="Data/Images/Icons/Collections - Green.png" inGameVisibility="0" mapDisplaySize="40"/>
                    <MarkerCategory name="astrolabe" DisplayName="Seer Astrolabe"  iconFile="Data/Images/Icons/Collections - Green.png" inGameVisibility="0" mapDisplaySize="40"/>
                    <MarkerCategory name="platter" DisplayName="Gold Ceremonial Platter"  iconFile="Data/Images/Icons/Collections - Green.png" inGameVisibility="0" mapDisplaySize="40"/>
                    <MarkerCategory name="tome" DisplayName="Ancient Tome"  iconFile="Data/Images/Icons/Collections - Green.png" inGameVisibility="0" mapDisplaySize="40"/>
                    <MarkerCategory name="isrsketch" DisplayName="Ineffable Spell Rune Sketch"  iconFile="Data/Images/Icons/Collections - Green.png" inGameVisibility="0" mapDisplaySize="40"/>
                    <MarkerCategory name="box" DisplayName="Misplaced Research Log Box"  iconFile="Data/Images/Icons/Collections - Green.png" inGameVisibility="0" mapDisplaySize="40"/>
                    <MarkerCategory name="tablet" DisplayName="Weathered Stone Tablet"  iconFile="Data/Images/Icons/Collections - Green.png" inGameVisibility="0" mapDisplaySize="40"/>
                    <MarkerCategory name="scroll" DisplayName="Crumbling Scroll"  iconFile="Data/Images/Icons/Collections - Green.png" inGameVisibility="0" mapDisplaySize="40"/>
                    <MarkerCategory name="vial" DisplayName="Vial of Whispering Water"  iconFile="Data/Images/Icons/Collections - Green.png" inGameVisibility="0" mapDisplaySize="40"/>
                    <MarkerCategory name="msrsketch" DisplayName="Murmuring Spell Rune Sketch"  iconFile="Data/Images/Icons/Collections - Green.png" inGameVisibility="0" mapDisplaySize="40"/>
                </MarkerCategory>

                <MarkerCategory name="entrance" DisplayName="Entrance to the Hidden Vault (Trail)">
                    <MarkerCategory name="icon" DisplayName="Toggle Icon" iconFile="Data/Images/Icons/Orb - Green - S.png" maxSize="16" mapDisplaySize="32" heightOffset="-0.25"/>
                    <MarkerCategory name="trail" DisplayName="Toggle Trail"/>
                </MarkerCategory>

                <MarkerCategory name="impulse" DisplayName="No Impulse Control" iconFile="Data/Images/Icons/Orb - Yellow - S.png" maxSize="16" mapDisplaySize="32" heightOffset="-0.25"/>

                
                <!-- CHAPTER 9 -->

                <MarkerCategory name="ch9" IsSeparator="1" DisplayName="CHAPTER 9: On the Threshold"/>

                <MarkerCategory name="thoughts" DisplayName="Any Last Thoughts" achievementId="9261" iconFile="Data/Images/Icons/Talk.png" minSize="20" maxSize="24" mapDisplaySize="48" inGameVisibility="0"/>

                <!-- CHAPTER 10 -->

                <MarkerCategory name="ch10" IsSeparator="1" DisplayName="CHAPTER 10: "/>

                <MarkerCategory name="ptoa" DisplayName="The Path of Ascension" achievementId="9301" iconFile="Data/Images/Icons/Talk.png" minSize="20" maxSize="24" mapDisplaySize="48">
                    <MarkerCategory name="icon" DisplayName="Toggle Icon" iconFile="Data/Images/Icons/Orb - Blue - S.png" maxSize="16" mapDisplaySize="32" heightOffset="-0.25"/>
                    <MarkerCategory name="trail" DisplayName="Toggle Trail" texture="Data/Images/Trails/Dashed Lines - Fine with Shadow.png" animSpeed="0"/>
                </MarkerCategory>
                <MarkerCategory name="infiltration" DisplayName="Infiltration Improvisation" achievementId="9308" iconFile="Data/Images/Icons/Collection - Story.png" mapDisplaySize="48" inGameVisibility="0">
                    <MarkerCategory name="ley" DisplayName="Raw Ley Magic" iconFile="Data/Images/Icons/Collections - Raw Ley Magic.png" achievementBit="1" mapDisplaySize="48" inGameVisibility="0" tip-name="Raw Ley Magic"/>
                    <MarkerCategory name="seer" DisplayName="Seer Magic" iconFile="Data/Images/Icons/Collections - Seer Magic.png" achievementBit="2" mapDisplaySize="48" inGameVisibility="0" tip-name="Seer Magic"/>
                    <MarkerCategory name="inquest" DisplayName="Inquest Magitech" iconFile="Data/Images/Icons/Collections - Inquest Magitech.png" achievementBit="3" mapDisplaySize="48" inGameVisibility="0" tip-name="Inquest Magitech"/>
                    <MarkerCategory name="saltpeter" DisplayName="Saltpeter" iconFile="Data/Images/Icons/Collections - Saltpeter.png" achievementBit="4" mapDisplaySize="48" inGameVisibility="0" tip-name="Saltpeter"/>
                    <MarkerCategory name="copper" DisplayName="Oxidised Copper" iconFile="Data/Images/Icons/Collections - Oxidised Copper.png" achievementBit="5" mapDisplaySize="48" inGameVisibility="0" tip-name="Oxidised Copper"/>
                    <MarkerCategory name="alum" DisplayName="Alum Crystal" iconFile="Data/Images/Icons/Collections - Alum Crystal.png" achievementBit="6" mapDisplaySize="48" inGameVisibility="0" tip-name="Alum Crystal"/>
                    <MarkerCategory name="pyrite" DisplayName="Pyrite Crystal" iconFile="Data/Images/Icons/Collections - Pyrite Crystal.png" achievementBit="7" mapDisplaySize="48" inGameVisibility="0" tip-name="Pyrite Crystal"/>
                    <MarkerCategory name="oil" DisplayName="Vial of Crude Oil" iconFile="Data/Images/Icons/Collections - Crude Oil.png" achievementBit="8" mapDisplaySize="48" inGameVisibility="0" tip-name="Crude Oil"/>
                    <MarkerCategory name="hourglass" DisplayName="Portable Hourglass" iconFile="Data/Images/Icons/Collections - Portable Hourglass.png" achievementBit="9" mapDisplaySize="48" inGameVisibility="0" tip-name="Portable Hourglass"/>
                    <MarkerCategory name="cell" DisplayName="Rudimentary Power Cell" iconFile="Data/Images/Icons/Collections - Rudimentary Power Cell.png" achievementBit="10" mapDisplaySize="48" inGameVisibility="0" tip-name="Power Cell"/>
                    <MarkerCategory name="metal" DisplayName="Sheet of Metal" iconFile="Data/Images/Icons/Collections - Sheet of Metal.png" achievementBit="11" mapDisplaySize="48" inGameVisibility="0" tip-name="Sheet of Metal"/>
                    <MarkerCategory name="leather" DisplayName="Leather Straps" iconFile="Data/Images/Icons/Collections - Leather Straps.png" achievementBit="12" mapDisplaySize="48" inGameVisibility="0" tip-name="Leather Straps"/>
                </MarkerCategory>
                
                <MarkerCategory name="meticulous" DisplayName="Meticulous Craftsperson" achievementId="9319">
                    <MarkerCategory name="pyrite" DisplayName="Pyrite Crystal" iconFile="Data/Images/Numbers/n1.png" minSize="12" maxSize="12"/>
                    <MarkerCategory name="ley" DisplayName="Raw Ley Magic" iconFile="Data/Images/Numbers/n2.png" minSize="12" maxSize="12"/>
                    <MarkerCategory name="seer" DisplayName="Seer Magic" iconFile="Data/Images/Numbers/n3.png" minSize="12" maxSize="12"/>
                    <MarkerCategory name="inquest" DisplayName="Inquest magitech" iconFile="Data/Images/Numbers/n4.png" minSize="12" maxSize="12"/>
                    <MarkerCategory name="solution" DisplayName="Canach's Solution" iconFile="Data/Images/Numbers/n5.png" minSize="12" maxSize="12"/>
                    <MarkerCategory name="saltpeter" DisplayName="Saltpeter" iconFile="Data/Images/Numbers/n6.png" minSize="12" maxSize="12"/>
                    <MarkerCategory name="alum" DisplayName="Alum crystal" iconFile="Data/Images/Numbers/n7.png" minSize="12" maxSize="12"/>
                    <MarkerCategory name="copper" DisplayName="Oxidised Copper" iconFile="Data/Images/Numbers/n8.png" minSize="12" maxSize="12"/>
                    <MarkerCategory name="cell" DisplayName="Power Cell" iconFile="Data/Images/Numbers/n9.png" minSize="12" maxSize="12"/>
                    <MarkerCategory name="metal" DisplayName="Sheet Metal" iconFile="Data/Images/Numbers/n10.png" minSize="12" maxSize="12"/>
                    <MarkerCategory name="hourglass" DisplayName="Portable hourglass" iconFile="Data/Images/Numbers/n11.png" minSize="12" maxSize="12"/>
                    <MarkerCategory name="leather" DisplayName="Leather Straps" iconFile="Data/Images/Numbers/n12.png" minSize="12" maxSize="12"/>
                </MarkerCategory>

                <!-- CHAPTER 11 -->
                
                <MarkerCategory name="ch11" IsSeparator="1" DisplayName="CHAPTER 11: "/>
                <MarkerCategory name="end" DisplayName="Ascension's End" achievementId="9340" iconFile="Data/Images/Icons/Orb - Blue.png" maxSize="24" mapDisplaySize="32" heightOffset="-0.5"/>
                <MarkerCategory name="astute" DisplayName="Astute Candidate" achievementId="9269" iconFile="Data/Images/Icons/Cog.png" maxSize="16" miniMapVisibility="0" mapVisibility="0" fadeNear="1200" fadeFar="1600"/>
                <MarkerCategory name="stalwart" DisplayName="Stalwart Candidate" achievementId="9332" miniMapVisibility="0" mapVisibility="0" fadeNear="1200" fadeFar="1600"/>
                
                <!-- CHAPTER 12 -->

                <MarkerCategory name="ch12" IsSeparator="1" DisplayName="CHAPTER 12: "/>

                <MarkerCategory name="diy" DisplayName="DIY Enthusiast" achievementId="9300" iconFile="Data/Images/Icons/Inquest Spanner.png" minSize="20" maxSize="24" mapDisplaySize="32" fadeNear="3000" fadeFar="4000"/>
                <MarkerCategory name="scouting" DisplayName="Scouting Report" achievementId="9316" iconFile="Data/Images/Icons/Orb - Red - S.png" minSize="20" maxSize="24" mapDisplaySize="32"/>
                <MarkerCategory name="twist" DisplayName="Twist the Knife" achievementId="9256" iconFile="Data/Images/Icons/Talk.png" minSize="20" maxSize="24" mapDisplaySize="40"/>
                
                <MarkerCategory name="ch13" IsSeparator="1" DisplayName="CHAPTER 13: "/>
                <MarkerCategory name="written" DisplayName="So it is Written" achievementId="9336">
                     <MarkerCategory name="joy" DisplayName="In Joyous Company" iconFile="Data/Images/Icons/VoE So It Is Written - In Joyous Company.png" maxSize="16"/>
                     <MarkerCategory name="perceptions" DisplayName="Perceptions Sharpened" iconFile="Data/Images/Icons/VoE So It Is Written - Perceptions Sharpened.png" maxSize="16"/>
                     <MarkerCategory name="weight" DisplayName="Weight of the Sky" iconFile="Data/Images/Icons/VoE So It Is Written - Weight of the Sky.png" maxSize="16"/>
                     <MarkerCategory name="ground" DisplayName="Above the Ground" iconFile="Data/Images/Icons/VoE So It Is Written - Above the Ground.png" maxSize="16"/>
                </MarkerCategory>

                <MarkerCategory name="guest" DisplayName="Honored Guest" achievementId="9299"  iconFile="Data/Images/Icons/Otter.png" minSize="20" maxSize="24" mapDisplaySize="32"/>

                <!--

                <MarkerCategory name="ch14" IsSeparator="1" DisplayName="CHAPTER 14: "/>
                <MarkerCategory name="" DisplayName="" achievementId="" iconFile="Data/Images/Icons/Orb - Blue.png" maxSize="16" heightOffset="-0.5"/>

                <MarkerCategory name="ch15" IsSeparator="1" DisplayName="CHAPTER 15: "/>
                <MarkerCategory name="" DisplayName="" achievementId="" iconFile="Data/Images/Icons/Orb - Blue.png" maxSize="16" heightOffset="-0.5"/>

                <MarkerCategory name="ch16" IsSeparator="1" DisplayName="CHAPTER 16: "/>
                <MarkerCategory name="" DisplayName="" achievementId="" iconFile="Data/Images/Icons/Orb - Blue.png" maxSize="16" heightOffset="-0.5"/>
                -->
            </MarkerCategory>


            <MarkerCategory name="map" IsSeparator="1" DisplayName="MAP ZONE"/>

            <MarkerCategory name="shipwreck" DisplayName="Shipwreck Strand">

                <MarkerCategory name="aasb" DisplayName="As Above, So Below" achievementId="9082">
                    <MarkerCategory name="high" DisplayName="High" iconFile="Data/Images/Icons/Object - Above.png" maxSize="32" mapDisplaySize="48" inGameVisibility="0"/>
                    <MarkerCategory name="low" DisplayName="Low" iconFile="Data/Images/Icons/Object - Below.png" maxSize="32" mapDisplaySize="48" inGameVisibility="0"/>
                </MarkerCategory>
                
                <MarkerCategory name="await" DisplayName="Await the Offgoing!" achievementId="9010" iconFile="Data/Images/Yellow Swirl.png" inGameVisibility="0" mapDisplaySize="128">
                    <MarkerCategory name="choya" DisplayName="Hidden Choya (Chance)" iconFile="Data/Images/Icons/Orb - Black and White - S.png" maxSize="16" mapDisplaySize="48" inGameVisibility="1"/>
                    <MarkerCategory name="nectar" DisplayName="Nectar of Divine Perception (for Chance to see Hidden Choya)" iconFile="Data/Images/Icons/Orb - Yellow - S.png" maxSize="16" mapDisplaySize="32" inGameVisibility="1"/>
                </MarkerCategory>

                <MarkerCategory name="aquatic" DisplayName="Aquatic Prison Break" achievementId="8875" iconFile="Data/Images/Yellow Swirl.png" mapDisplaySize="128" inGameVisibility="0"/>

                <MarkerCategory name="captain" DisplayName="Captain Leo the Relentless (After Meta)" achievementId="9021">
                    <MarkerCategory name="set" IsSeparator="1" DisplayName="SETTINGS"/>
                    <MarkerCategory name="wp" DisplayName="Toggle Waypoint Markers" iconFile="Data/Images/Icons/Blank.png" triggerrange="2" autotrigger="true"/>
                    <MarkerCategory name="mount" DisplayName="Mounts" miniMapVisibility="0" minSize="24" maxSize="32">
                        <MarkerCategory name="skimmer" DisplayName="Skimmer" iconFile="Data/Images/Mounts/Mount_Skimmer.png"/>
                        <MarkerCategory name="skyscale" DisplayName="Skyscale" iconFile="Data/Images/Mounts/Mount_Skyscale.png"/>
                        <MarkerCategory name="springer" DisplayName="Springer" iconFile="Data/Images/Mounts/Mount_Springer.png"/>
                    </MarkerCategory>
                    <MarkerCategory name="numbers" DisplayName="Trail Number">
                        <MarkerCategory name="1" DisplayName="One" iconFile="Data/Images/Numbers/1.png" miniMapVisibility="0" minSize="16" maxSize="24"/>
                        <MarkerCategory name="2" DisplayName="Two" iconFile="Data/Images/Numbers/2.png" miniMapVisibility="0" minSize="16" maxSize="24"/>
                        <MarkerCategory name="3" DisplayName="Three" iconFile="Data/Images/Numbers/3.png" miniMapVisibility="0" minSize="16" maxSize="24"/>
                        <MarkerCategory name="4" DisplayName="Four" iconFile="Data/Images/Numbers/4.png" miniMapVisibility="0" minSize="16" maxSize="24"/>
                        <MarkerCategory name="5" DisplayName="Five" iconFile="Data/Images/Numbers/5.png" miniMapVisibility="0" minSize="16" maxSize="24"/>
                        <MarkerCategory name="6" DisplayName="Six" iconFile="Data/Images/Numbers/6.png" miniMapVisibility="0" minSize="16" maxSize="24"/>
                    </MarkerCategory>

                    <MarkerCategory name="obj" IsSeparator="1" DisplayName="OBJECTIVES"/>
                    <MarkerCategory name="book" DisplayName="Toggle Book Icon" iconFile="Data/Images/Icons/Captain Leo the Relentless.png" mapDisplaySize="32" inGameVisibility="0"/>
                    <MarkerCategory name="boy" DisplayName="Find the cabin boy" iconFile="Data/Images/Icons/Orb - Red - S.png" maxSize="16" mapDisplaySize="32" heightOffset="-0.25"/>
                    <MarkerCategory name="sailor" DisplayName="Find the sailor" iconFile="Data/Images/Icons/Orb - Red - S.png" maxSize="16" mapDisplaySize="32" heightOffset="-0.25"/>
                    <MarkerCategory name="gunner" DisplayName="Find the gunner" iconFile="Data/Images/Icons/Orb - Red - S.png" maxSize="16" mapDisplaySize="32" heightOffset="-0.25"/>
                    <MarkerCategory name="navigator" DisplayName="Find the navigator" iconFile="Data/Images/Icons/Orb - Red - S.png" maxSize="16" mapDisplaySize="32" heightOffset="-0.25"/>
                    <MarkerCategory name="cook" DisplayName="Find the cook" iconFile="Data/Images/Icons/Orb - Red - S.png" maxSize="16" mapDisplaySize="32" heightOffset="-0.25"/>
                    <MarkerCategory name="boatswain" DisplayName="Find the boatswain" iconFile="Data/Images/Icons/Orb - Red - S.png" maxSize="16" mapDisplaySize="32" heightOffset="-0.25"/>
                    <MarkerCategory name="arms" DisplayName="Find the master-at-arms" iconFile="Data/Images/Icons/Orb - Red - S.png" maxSize="16" mapDisplaySize="32" heightOffset="-0.25"/>
                    <MarkerCategory name="quarter" DisplayName="Find the quartermaster" iconFile="Data/Images/Icons/Orb - Red - S.png" maxSize="16" mapDisplaySize="32" heightOffset="-0.25"/>
                    <MarkerCategory name="mate" DisplayName="Find the first mate" iconFile="Data/Images/Icons/Orb - Red - S.png" maxSize="16" mapDisplaySize="32" heightOffset="-0.25"/>
                    <MarkerCategory name="captain" DisplayName="Find Captain Leo the Relentless" iconFile="Data/Images/Icons/Orb - Red - S.png" maxSize="16" mapDisplaySize="32" heightOffset="-0.25"/>
                </MarkerCategory>

                <MarkerCategory name="samantha" DisplayName="Converse with Samantha" achievementId="9054" iconFile="Data/Images/Icons/Samantha.png" maxSize="16" mapDisplaySize="32"/>

                <MarkerCategory name="wavehawks" DisplayName="Do Feed the Wavehawks" achievementId="8957" iconFile="Data/Images/Icons/Wavehawk Treat.png" maxSize="16" mapDisplaySize="32"/>

                <MarkerCategory name="dog" DisplayName="Dog Trainer" achievementId="9001" iconFile="Data/Images/Icons/Shrimpy.png" maxSize="24" mapDisplaySize="48" info="TIP: Look for nearby Dog Treats" infoRange="5"/>
    
                <MarkerCategory name="loopy" DisplayName="Feeling Loopy" achievementId="8991" iconFile="Data/Images/Icons/Stone Loop.png" inGameVisibility="0" mapDisplaySize="64"/>
                
                <MarkerCategory name="initiate" DisplayName="Freebooter Initiate" achievementId="8882">
                    <MarkerCategory name="set" IsSeparator="1" DisplayName="SETTINGS"/>
                    <MarkerCategory name="sign" DisplayName="Toggle Sign" iconFile="Data/Images/Mini-Dungeons/Freebooter Initiate.png" miniMapVisibility="1" mapVisibility="1" inGameVisibility="0" mapDisplaySize="96"/>
                </MarkerCategory>

                <MarkerCategory name="ghosts" DisplayName="Ghosts Need Friends Too" achievementId="8971" iconFile="Data/Images/Icons/Ghost Child.png" maxSize="32" mapDisplaySize="32"/>

                <MarkerCategory name="boot" DisplayName="Give 'Em the Boot" achievementId="8935">
                    <MarkerCategory name="escort" DisplayName="Escort the castaways into freebooter territory" iconFile="Data/Images/Yellow Swirl.png" inGameVisibility="0" mapDisplaySize="128"/>
                    <MarkerCategory name="hammerhart" DisplayName="Successfully complete the Hammerhart Rumble [World Boss]" iconFile="Data/Images/Yellow Swirl.png" inGameVisibility="0" mapDisplaySize="128"/>
                    <MarkerCategory name="hullgardener" DisplayName="Defend the Hullgardeners' territory" iconFile="Data/Images/Yellow Swirl.png" inGameVisibility="0" mapDisplaySize="128"/>
                    <MarkerCategory name="wavehawk" DisplayName="Rescue the Wavehawks" iconFile="Data/Images/Yellow Swirl.png" inGameVisibility="0" mapDisplaySize="128"/>
                    <MarkerCategory name="recruiter" DisplayName="Stop a Recruiter" iconFile="Data/Images/Icons/Brawl.png" inGameVisibility="0" mapDisplaySize="32"/>
                    <MarkerCategory name="tennet" DisplayName="Defeat Boatswain Tennet" iconFile="Data/Images/Boatswain Tennet.png" inGameVisibility="0" mapDisplaySize="48"/>
                </MarkerCategory>

                <MarkerCategory name="glimmering" DisplayName="Glimmering Arches Grand Prix" achievementId="8921">
                    <MarkerCategory name="set" IsSeparator="1" DisplayName="SETTINGS"/>
                    <MarkerCategory name="sign" DisplayName="Toggle Sign" iconFile="Data/Images/Adventures/Glimmering Arches Grand Prix.png" miniMapVisibility="1" mapVisibility="1" inGameVisibility="0" mapDisplaySize="96"/>
                </MarkerCategory>

                <MarkerCategory name="grotto" DisplayName="Grotto Aficionado [H]" achievementId="8873" iconFile="Data/Images/Swirl - Teal.png" inGameVisibility="0" mapDisplaySize="128">
                    <MarkerCategory name="set" IsSeparator="1" DisplayName="SETTINGS"/>
                    <MarkerCategory name="caves" DisplayName="Underwater Caves" mapDisplaySize="16" inGameVisibility="0"/>
                    <MarkerCategory name="grotto" IsSeparator="1" DisplayName="GROTTO'S"/>
                    <MarkerCategory name="starry" DisplayName="Starry Grotto"/>
                    <MarkerCategory name="quiggles" DisplayName="Quiggles Hideaway"/>
                    <MarkerCategory name="flotsam" DisplayName="Flotsam Grotto"/>
                    <MarkerCategory name="monument" DisplayName="Monument Grotto"/>
                    <MarkerCategory name="ship" DisplayName="Ship-In-A-Bottle Grotto"/>
                    <MarkerCategory name="waterfall" DisplayName="Waterfall Rest Grotto"/>
                    <MarkerCategory name="chamber" DisplayName="Chamber of Rising Petals"/>
                    <MarkerCategory name="blooming" DisplayName="Blooming Branch Grotto"/>
                    <MarkerCategory name="overgrown" DisplayName="Overgrown Channel Grotto"/>
                    <MarkerCategory name="orb" DisplayName="The Orb Cavern"/>
                    <MarkerCategory name="booters" DisplayName="'Booter's Hidey-Hole"/>
                </MarkerCategory>

                <MarkerCategory name="thirsty" DisplayName="Help the Thirsty Old Captain [H]" achievementId="9081" texture="Data/Images/Trails/Dashed Lines Dark - Fine with Shadow.png"/>

                <MarkerCategory name="quiggles" DisplayName="Hidden Quiggles" achievementId="8953" iconFile="Data/Images/Icons/Mr Quiggles.png" maxSize="32" mapDisplaySize="32"/>

                <MarkerCategory name="hobbies" DisplayName="Hobbies of the Hullgardeners" achievementId="8893">
                    <MarkerCategory name="kite" DisplayName="Fly a Kite" iconFile="Data/Images/Icons/Kite.png" inGameVisibility="0" mapDisplaySize="48"/>
                    <MarkerCategory name="boat" DisplayName="Make a paper boat and set sail" iconFile="Data/Images/Icons/Paper Boat.png" inGameVisibility="0" mapDisplaySize="32"/>
                    <MarkerCategory name="flowers" DisplayName="Pick flowers for a local couple">
                        <MarkerCategory name="icon" DisplayName="Pretty Flowers" iconFile="Data/Images/Icons/Flower.png" inGameVisibility="0" mapDisplaySize="40"/>
                    </MarkerCategory>
                    <MarkerCategory name="shells" DisplayName="Help collect shells, and give them to Sheldon" iconFile="Data/Images/Icons/Shells.png" inGameVisibility="0" mapDisplaySize="32"/>
                </MarkerCategory>

                <MarkerCategory name="crabe" DisplayName="In a Pinch" achievementId="8934">
                    <MarkerCategory name="alex" DisplayName="Help Acolyte Alex return the beached whale to the shelter of the sea" iconFile="Data/Images/Icons/Acolyte Alex.png" mapDisplaySize="48" inGameVisibility="0"/>
                    <MarkerCategory name="sorcha" DisplayName="Help Fisher Sorcha pull the beached whale back into the water" iconFile="Data/Images/Icons/Fisher Sorcha.png" mapDisplaySize="48" inGameVisibility="0"/>
                    <MarkerCategory name="hullgardeners" DisplayName="Keep the Hullgardeners comfortable while they work on their tans" iconFile="Data/Images/Yellow Swirl.png" mapDisplaySize="128" inGameVisibility="0"/>
                    <MarkerCategory name="sharpclaw" DisplayName="Guide crabs to Sharpclaw to help him make an offering to Kela" iconFile="Data/Images/Icons/Sharpclaw.png" mapDisplaySize="48" inGameVisibility="0"/>
                    <MarkerCategory name="crabs" DisplayName="Calm the crabby crabs" iconFile="Data/Images/Icons/Narcisse.png" mapDisplaySize="48" inGameVisibility="0"/>
                </MarkerCategory>
                
                <MarkerCategory name="memory" DisplayName="In Loving Memory" achievementId="8926" iconFile="Data/Images/Icons/Orb - White Shadow - S.png" maxSize="16">
                    <MarkerCategory name="set" IsSeparator="1" DisplayName="SETTINGS"/>
                    <MarkerCategory name="start" DisplayName="Toggle Start Marker" iconFile="Data/Images/Icons/Start.png" miniMapVisibility="1" mapVisibility="1" inGameVisibility="0" mapDisplaySize="128"/>
                    <MarkerCategory name="wp" DisplayName="Toggle Waypoint Markers" iconFile="Data/Images/Icons/Blank.png" triggerrange="2" autotrigger="true"/>
                    <MarkerCategory name="mount" DisplayName="Mounts" miniMapVisibility="0" minSize="24" maxSize="32">
                        <MarkerCategory name="skimmer" DisplayName="Skimmer" iconFile="Data/Images/Mounts/Mount_Skimmer.png"/>
                        <MarkerCategory name="skyscale" DisplayName="Skyscale" iconFile="Data/Images/Mounts/Mount_Skyscale.png"/>
                        <MarkerCategory name="springer" DisplayName="Springer" iconFile="Data/Images/Mounts/Mount_Springer.png"/>
                    </MarkerCategory>
                    <MarkerCategory name="numbers" DisplayName="Trail Number">
                        <MarkerCategory name="1" DisplayName="One" iconFile="Data/Images/Numbers/1.png" miniMapVisibility="0" minSize="16" maxSize="24"/>
                        <MarkerCategory name="2" DisplayName="Two" iconFile="Data/Images/Numbers/2.png" miniMapVisibility="0" minSize="16" maxSize="24"/>
                        <MarkerCategory name="3" DisplayName="Three" iconFile="Data/Images/Numbers/3.png" miniMapVisibility="0" minSize="16" maxSize="24"/>
                        <MarkerCategory name="4" DisplayName="Four" iconFile="Data/Images/Numbers/4.png" miniMapVisibility="0" minSize="16" maxSize="24"/>
                        <MarkerCategory name="5" DisplayName="Five" iconFile="Data/Images/Numbers/5.png" miniMapVisibility="0" minSize="16" maxSize="24"/>
                    </MarkerCategory>
                    <MarkerCategory name="obj" IsSeparator="1" DisplayName="OBJECTIVES"/>
                    <MarkerCategory name="bouquet" DisplayName="A bouquet of flowers is placed here"/>
                    <MarkerCategory name="grave" DisplayName="Tove grieves at this grave"/>
                    <MarkerCategory name="candles" DisplayName="A pair of candles, lit for a pair"/>
                    <MarkerCategory name="buried" DisplayName="A grave where rumors are buried"/>
                    <MarkerCategory name="monument" DisplayName="A monument in a grotto; a majesty and a memorial to many"/>
                    <MarkerCategory name="1" DisplayName="Under the earth, in a grotto. The first of a trio"/>
                    <MarkerCategory name="2" DisplayName="Under the earth, in a grotto. The second of a trio"/>
                    <MarkerCategory name="3" DisplayName="Under the earth, in a grotto. The third of a trio"/>
                    <MarkerCategory name="warrior" DisplayName="A warrior's grave, watching those in the village from a distance"/>
                </MarkerCategory>
                
                <MarkerCategory name="lost" DisplayName="Lost Loved Ones" achievementId="8961">
                    <MarkerCategory name="set" IsSeparator="1" DisplayName="SETTINGS"/>
                    <MarkerCategory name="start" DisplayName="Toggle Start Marker" iconFile="Data/Images/Icons/Start.png" miniMapVisibility="1" mapVisibility="1" inGameVisibility="0" mapDisplaySize="128"/>
                    <MarkerCategory name="wp" DisplayName="Toggle Waypoint Markers" iconFile="Data/Images/Icons/Blank.png" triggerrange="2" autotrigger="true"/>
                    <MarkerCategory name="mount" DisplayName="Mounts" miniMapVisibility="0" minSize="24" maxSize="32">
                        <MarkerCategory name="skimmer" DisplayName="Skimmer" iconFile="Data/Images/Mounts/Mount_Skimmer.png"/>
                        <MarkerCategory name="skyscale" DisplayName="Skyscale" iconFile="Data/Images/Mounts/Mount_Skyscale.png"/>
                        <MarkerCategory name="springer" DisplayName="Springer" iconFile="Data/Images/Mounts/Mount_Springer.png"/>
                    </MarkerCategory>
                    <MarkerCategory name="numbers" DisplayName="Trail Number">
                        <MarkerCategory name="1" DisplayName="One" iconFile="Data/Images/Numbers/1.png" miniMapVisibility="0" minSize="16" maxSize="24"/>
                        <MarkerCategory name="2" DisplayName="Two" iconFile="Data/Images/Numbers/2.png" miniMapVisibility="0" minSize="16" maxSize="24"/>
                        <MarkerCategory name="3" DisplayName="Three" iconFile="Data/Images/Numbers/3.png" miniMapVisibility="0" minSize="16" maxSize="24"/>
                        <MarkerCategory name="4" DisplayName="Four" iconFile="Data/Images/Numbers/4.png" miniMapVisibility="0" minSize="16" maxSize="24"/>
                        <MarkerCategory name="5a" DisplayName="Five a" iconFile="Data/Images/Numbers/5a.png" miniMapVisibility="0" minSize="16" maxSize="24"/>
                        <MarkerCategory name="5b" DisplayName="Five b" iconFile="Data/Images/Numbers/5b.png" miniMapVisibility="0" minSize="16" maxSize="24"/>
                        <MarkerCategory name="5c" DisplayName="Five c" iconFile="Data/Images/Numbers/5c.png" miniMapVisibility="0" minSize="16" maxSize="24"/>
                        <MarkerCategory name="5d" DisplayName="Five d" iconFile="Data/Images/Numbers/5d.png" miniMapVisibility="0" minSize="16" maxSize="24"/>
                        <MarkerCategory name="5e" DisplayName="Five e" iconFile="Data/Images/Numbers/5e.png" miniMapVisibility="0" minSize="16" maxSize="24"/>
                        <MarkerCategory name="5f" DisplayName="Five f" iconFile="Data/Images/Numbers/5f.png" miniMapVisibility="0" minSize="16" maxSize="24"/>
                        <MarkerCategory name="5g" DisplayName="Five g" iconFile="Data/Images/Numbers/5g.png" miniMapVisibility="0" minSize="16" maxSize="24"/>
                        <MarkerCategory name="6" DisplayName="Six" iconFile="Data/Images/Numbers/6.png" miniMapVisibility="0" minSize="16" maxSize="24"/>
                    </MarkerCategory>
                    <MarkerCategory name="obj" IsSeparator="1" DisplayName="OBJECTIVES"/>
                    <MarkerCategory name="message" DisplayName="Find the Message in a Bottle" iconFile="Data/Images/Icons/Collections.png" inGameVisibility="0" maxSize="16" mapDisplaySize="32"/>
                    <MarkerCategory name="lyla" DisplayName="Castaway Lyla" iconFile="Data/Images/Icons/Talk.png" maxSize="48" miniMapVisibility="0" mapVisibility="0"/>
                    <MarkerCategory name="token" DisplayName="Bring Lyla's Token to the remains" iconFile="Data/Images/Icons/Collections.png" inGameVisibility="0" mapDisplaySize="32"/>
                    <MarkerCategory name="harvey" DisplayName="5a. Leave gold at Harvey's resting place" iconFile="Data/Images/Icons/Collections.png" inGameVisibility="0" mapDisplaySize="32"/>
                    <MarkerCategory name="mikki" DisplayName="5b. Light candles at Mikki's parents' grave" iconFile="Data/Images/Icons/Collections.png" inGameVisibility="0" mapDisplaySize="32"/>
                    <MarkerCategory name="liz" DisplayName="5c. Get a musical instrument for Liz" iconFile="Data/Images/Icons/Castaway Dampfur.png" inGameVisibility="0" mapDisplaySize="32"/>
                    <MarkerCategory name="5d" DisplayName="5d. Play Liz's Song near where she was last seen" iconFile="Data/Images/Icons/Collections.png" inGameVisibility="0" mapDisplaySize="32"/>
                    <MarkerCategory name="5e" DisplayName="5e. Pick a bouquet for Robert and leave it by his grave" iconFile="Data/Images/Icons/Collections.png" inGameVisibility="0" mapDisplaySize="32"/>
                    <MarkerCategory name="5f" DisplayName="5f. Place a stone on Pine's resting place" iconFile="Data/Images/Icons/Collections.png" inGameVisibility="0" mapDisplaySize="32"/>
                    <MarkerCategory name="5g" DisplayName="5g. Go to Gertie's grave on a spire over shipwrecks" iconFile="Data/Images/Icons/Collections.png" inGameVisibility="0" mapDisplaySize="32"/>
                    <MarkerCategory name="6" DisplayName="Seek me out once more; return to my remains where you left the bottle" iconFile="Data/Images/Icons/Collections.png" inGameVisibility="0" mapDisplaySize="32"/>
                    <MarkerCategory name="7" DisplayName="Reunite Karina and Lyla" iconFile="Data/Images/Icons/Talk.png" inGameVisibility="0" mapDisplaySize="32"/>
                    <MarkerCategory name="8" DisplayName="Let Amy May know you helped" iconFile="Data/Images/Icons/Talk.png" inGameVisibility="0" mapDisplaySize="32"/>
                </MarkerCategory>
                
                <MarkerCategory name="moat" DisplayName="Memories of Another Time" achievementId="8854">
                    <MarkerCategory name="req" IsSeparator="1" DisplayName="REQ: Ch.5: Truths Unearthed"/>
                    <MarkerCategory name="set" IsSeparator="1" DisplayName="SETTINGS"/>
                    <MarkerCategory name="start" DisplayName="Toggle Start Marker" iconFile="Data/Images/Icons/Start.png" miniMapVisibility="1" mapVisibility="1" inGameVisibility="0" mapDisplaySize="128"/>
                    <MarkerCategory name="wp" DisplayName="Toggle Waypoint Markers" iconFile="Data/Images/Icons/Blank.png" triggerrange="2" autotrigger="true"/>
                    <MarkerCategory name="mount" DisplayName="Mounts" miniMapVisibility="0" minSize="24" maxSize="32">
                        <MarkerCategory name="skimmer" DisplayName="Skimmer" iconFile="Data/Images/Mounts/Mount_Skimmer.png"/>
                        <MarkerCategory name="skyscale" DisplayName="Skyscale" iconFile="Data/Images/Mounts/Mount_Skyscale.png"/>
                        <MarkerCategory name="springer" DisplayName="Springer" iconFile="Data/Images/Mounts/Mount_Springer.png"/>
                    </MarkerCategory>
                    <MarkerCategory name="numbers" DisplayName="Trail Number">
                        <MarkerCategory name="1" DisplayName="One" iconFile="Data/Images/Numbers/1.png" miniMapVisibility="0" minSize="16" maxSize="24"/>
                        <MarkerCategory name="2" DisplayName="Two" iconFile="Data/Images/Numbers/2.png" miniMapVisibility="0" minSize="16" maxSize="24"/>
                        <MarkerCategory name="3" DisplayName="Three" iconFile="Data/Images/Numbers/3.png" miniMapVisibility="0" minSize="16" maxSize="24"/>
                        <MarkerCategory name="4" DisplayName="Four" iconFile="Data/Images/Numbers/4.png" miniMapVisibility="0" minSize="16" maxSize="24"/>
                        <MarkerCategory name="5" DisplayName="Five" iconFile="Data/Images/Numbers/5.png" miniMapVisibility="0" minSize="16" maxSize="24"/>
                    </MarkerCategory>
                    <MarkerCategory name="obj" IsSeparator="1" DisplayName="OBJECTIVES"/>
                    <MarkerCategory name="1" DisplayName="Speak with a former Astral Ward member in Glimmering Arches" iconFile="Data/Images/Icons/Talk.png" maxSize="24"/>
                    <MarkerCategory name="2" DisplayName="Look for a memory on a cliff between garden, glade, and hollows in Shipwreck Strand" iconFile="Data/Images/Icons/Orb - Blue - S.png"/>
                    <MarkerCategory name="3" DisplayName="Central Tyria: Pay a visit back to a fiefdom that gazes up at the Wizard's Tower" iconFile="Data/Images/Icons/Orb - Blue - S.png"/>
                    <MarkerCategory name="4" DisplayName="Shipwreck Strand: on a small island of plants and wildlife." iconFile="Data/Images/Icons/Orb - Blue - S.png"/>
                    <MarkerCategory name="5" DisplayName="Starlit Weald: north of a ruin's moat." iconFile="Data/Images/Icons/Orb - Blue - S.png"/>
                    <MarkerCategory name="6" DisplayName="Speak to the foremost expert on the Astral Ward in Shipwreck Strand." iconFile="Data/Images/Icons/Orb - Blue - S.png"/>
                    <MarkerCategory name="7" DisplayName="Look for a memory washed to shore among the shipwrecks of the southern strand." iconFile="Data/Images/Icons/Orb - Blue - S.png"/>
                    <MarkerCategory name="8" DisplayName="Central Tyria: track down a memory bidding farewell to a pair of steadfast hawks." iconFile="Data/Images/Icons/Orb - Blue - S.png"/>
                    <MarkerCategory name="9" DisplayName="Travel to the source of undead draconic magic in Central Tyria" iconFile="Data/Images/Icons/Orb - Blue - S.png"/>
                    <MarkerCategory name="10" DisplayName="Return the memories to the former Astral Ward member in Glimmering Arches." iconFile="Data/Images/Icons/Orb - Blue - S.png"/>
                </MarkerCategory>

                <MarkerCategory name="cavern" DisplayName="Orb Cavern Jumping Puzzle" achievementId="8932">
                    <MarkerCategory name="set" IsSeparator="1" DisplayName="SETTINGS"/>
                    <MarkerCategory name="sign" DisplayName="Toggle Sign" iconFile="Data/Images/Jumping Puzzles/Orb Cavern.png" miniMapVisibility="1" mapVisibility="1" inGameVisibility="0" mapDisplaySize="96"/>
                    <MarkerCategory name="glider" DisplayName="Toggle Glider" iconFile="Data/Images/Icons/Glider.png" maxSize="24" inGameVisibility="1" fadeNear="900" fadeFar="1200" miniMapVisibility="0"/>
                </MarkerCategory>

                <MarkerCategory name="paxx" DisplayName="Paxx's Favorite Patron" achievementId="9052" iconFile="Data/Images/Icons/Paxx's Favourite Patron.png" maxSize="24" mapDisplaySize="48"/>
                
                <MarkerCategory name="plague" DisplayName="Plague Doctor" achievementId="8963" iconFile="Data/Images/Yellow Swirl.png" mapDisplaySize="128"/>
                
                <MarkerCategory name="ponder" DisplayName="Ponder the Pools" achievementId="8950" iconFile="Data/Images/Icons/Tide Pool.png" maxSize="16" mapDisplaySize="48"/>

                <MarkerCategory name="freshwater" DisplayName="Shipwreck Strand's Freshest Water" achievementId="9051" iconFile="Data/Images/Thirsty.png" maxSize="16" mapDisplaySize="48"/>
                <MarkerCategory name="scramble" DisplayName="Skimmer-Net Scramble" achievementId="8860">
                    <MarkerCategory name="set" IsSeparator="1" DisplayName="SETTINGS"/>
                    <MarkerCategory name="sign" DisplayName="Toggle Sign" iconFile="Data/Images/Adventures/Skimmer-Net Scramble.png" miniMapVisibility="1" mapVisibility="1" inGameVisibility="0" mapDisplaySize="96"/>
                </MarkerCategory>
                
                <MarkerCategory name="copse" DisplayName="Soaring Copse Jumping Puzzle" achievementId="8976" fadeNear="1200" fadeFar="2400">
                    <MarkerCategory name="set" IsSeparator="1" DisplayName="SETTINGS"/>
                    <MarkerCategory name="sign" DisplayName="Toggle Sign" iconFile="Data/Images/Jumping Puzzles/Soaring Copse.png" miniMapVisibility="1" mapVisibility="1" inGameVisibility="0" mapDisplaySize="96"/>
                    <MarkerCategory name="talk" DisplayName="Talk to Astral Ward Researcher Harpa" iconFile="Data/Images/Icons/Talk.png" maxSize="48"/>
                    <MarkerCategory name="glider" DisplayName="Toggle Glider" iconFile="Data/Images/Icons/Glider.png" maxSize="24" inGameVisibility="1"/>
                </MarkerCategory>

                <MarkerCategory name="fireworks" DisplayName="Soaring Sands Fireworks" achievementId="9058" texture="Data/Images/Trails/Line - Medium Wide with Shadow.png" animSpeed="0">
                    <MarkerCategory name="set" IsSeparator="1" DisplayName="SETTINGS"/>
                    <MarkerCategory name="sign" DisplayName="Toggle Sign" iconFile="Data/Images/Adventures/Flying Fireworks.png" miniMapVisibility="1" mapVisibility="1" inGameVisibility="0" mapDisplaySize="96"/>
                    <MarkerCategory name="colors" IsSeparator="1" DisplayName="COLOURS"/>
                    <MarkerCategory name="red" DisplayName="Red" iconFile="Data/Images/Icons/Orb - Red - S.png" maxSize="16" mapDisplaySize="32"/>
                    <MarkerCategory name="yellow" DisplayName="Yellow" iconFile="Data/Images/Icons/Orb - Yellow - S.png" maxSize="16" mapDisplaySize="32" fadeNear="5000" fadeFar="7500"/>
                    <MarkerCategory name="blue" DisplayName="Blue" iconFile="Data/Images/Icons/Orb - Blue - S.png" maxSize="16" mapDisplaySize="32" fadeNear="5000" fadeFar="7500"/>
                </MarkerCategory>
                
                <MarkerCategory name="lesser" DisplayName="The Lesser-Known Leaders of Shipwreck Strand" achievementId="8861">
                    <MarkerCategory name="king" DisplayName="Meet and defeat the rat king." iconFile="Data/Images/Rat King.png" inGameVisibility="0" mapDisplaySize="64"/>
                    <MarkerCategory name="royalty" DisplayName="Meet wannabe freebooter royalty Jessica and Jimmy [Meta]">
                        <MarkerCategory name="Jessica" DisplayName="Captain Jessica Hammerhart" iconFile="Data/Images/Captain Jessica Hammerhart.png" inGameVisibility="0" mapDisplaySize="64"/>
                        <MarkerCategory name="Jimmy" DisplayName="First Mate Jimmy Hammerhart" iconFile="Data/Images/First Mate Jimmy Hammerhart.png" inGameVisibility="0" mapDisplaySize="64"/>
                    </MarkerCategory>
                    <MarkerCategory name="ursulette" DisplayName="Meet the leader of suntanning castaways" iconFile="Data/Images/Castaway Ursulette.png" inGameVisibility="0" mapDisplaySize="48"/>
                    <MarkerCategory name="avyn" DisplayName="Meet Adherent Avyn" iconFile="Data/Images/Adherent Avyn.png" inGameVisibility="0" mapDisplaySize="64"/>
                    <MarkerCategory name="crabs" DisplayName="Calm the Crabby Crabs" iconFile="Data/Images/King Crab.png" inGameVisibility="0" mapDisplaySize="64"/>
                    <MarkerCategory name="kash" DisplayName="Meet Kash and help them lead the Hullgardeners" iconFile="Data/Images/Swirl - Golden.png" inGameVisibility="0" mapDisplaySize="128"/>
                </MarkerCategory>
                
                <MarkerCategory name="tomes" DisplayName="Tropical Tomes" achievementId="8894" iconFile="Data/Images/Icons/Journal Fragment.png" maxSize="16" mapDisplaySize="32">
                    <MarkerCategory name="letter" DisplayName="Letter" iconFile="Data/Images/Icons/Orb - Yellow - S.png" maxSize="16" achievementBit="0"/>
                    <MarkerCategory name="record" DisplayName="Transaction Record" iconFile="Data/Images/Icons/Orb - Yellow - S.png" maxSize="16" achievementBit="1"/>
                    <MarkerCategory name="whales" DisplayName="On the Beaching of Whales" iconFile="Data/Images/Icons/Orb - Yellow - S.png" maxSize="16" achievementBit="2"/>
                    <MarkerCategory name="captain" DisplayName="Captain's Journal" iconFile="Data/Images/Icons/Orb - Yellow - S.png" maxSize="16" achievementBit="3"/>
                    <MarkerCategory name="arrival" DisplayName="Peculiar Arrival" iconFile="Data/Images/Icons/Orb - Yellow - S.png" maxSize="16" achievementBit="4"/>
                    <MarkerCategory name="westergard" DisplayName="Westergard's Journal" iconFile="Data/Images/Icons/Orb - Yellow - S.png" maxSize="16" achievementBit="5"/>
                    <MarkerCategory name="osborne" DisplayName="Osborn'e Journal" iconFile="Data/Images/Icons/Orb - Yellow - S.png" maxSize="16" achievementBit="6"/>
                    <MarkerCategory name="notice" DisplayName="Notice: Procedure for handling new castaways" iconFile="Data/Images/Icons/Talk.png" maxSize="16" info="Requires: Tier 2 Hullgarden Renown Mastery" infoRange="5" achievementBit="7"/>
                    <MarkerCategory name="tattered" DisplayName="Tattered Journal" iconFile="Data/Images/Icons/Orb - Yellow - S.png" maxSize="16" achievementBit="8"/>
                    <MarkerCategory name="jernal" DisplayName="My Jernal" iconFile="Data/Images/Icons/Orb - Yellow - S.png" maxSize="16" achievementBit="9"/>
                    <MarkerCategory name="req" IsSeparator="1" DisplayName="REQUIRE: Tier 3 Hullgarden Renown Mastery"/>
                    <MarkerCategory name="rock" DisplayName="The Lonely Rock" iconFile="Data/Images/Icons/Orb - Yellow - S.png" maxSize="16" heightOffset="-0.25" achievementBit="10"/>
                    <MarkerCategory name="grammie" DisplayName="Grammie West's Best Recipe, Vol. 96" iconFile="Data/Images/Icons/Orb - Yellow - S.png" maxSize="16" heightOffset="-0.25" achievementBit="11"/>
                    <MarkerCategory name="complaints" DisplayName="Complaints" iconFile="Data/Images/Icons/Orb - Yellow - S.png" maxSize="16" heightOffset="-0.25" achievementBit="12"/>
                </MarkerCategory>

                <MarkerCategory name="skritcher" DisplayName="Wavehawk Scritcher" achievementId="8981" iconFile="Data/Images/Icons/Wavehawk.png" inGameVisibility="0" mapDisplaySize="32">
                    <MarkerCategory name="1" DisplayName="#1"/>
                    <MarkerCategory name="2" DisplayName="#2"/>
                    <MarkerCategory name="3" DisplayName="#3"/>
                    <MarkerCategory name="4" DisplayName="#4"/>
                    <MarkerCategory name="5" DisplayName="#5"/>
                    <MarkerCategory name="6" DisplayName="#6"/>
                    <MarkerCategory name="7" DisplayName="#7"/>
                    <MarkerCategory name="8" DisplayName="#8"/>
                    <MarkerCategory name="9" DisplayName="#9"/>
                    <MarkerCategory name="10" DisplayName="#10"/>
                    <MarkerCategory name="11" DisplayName="#11"/>
                    <MarkerCategory name="12" DisplayName="#12"/>
                    <MarkerCategory name="13" DisplayName="#13"/>
                    <MarkerCategory name="14" DisplayName="#14"/>
                    <MarkerCategory name="15" DisplayName="#15"/>
                    <MarkerCategory name="16" DisplayName="#16"/>
                    <MarkerCategory name="17" DisplayName="#17"/>
                    <MarkerCategory name="18" DisplayName="#18"/>
                    <MarkerCategory name="19" DisplayName="#19"/>
                    <MarkerCategory name="20" DisplayName="#20"/>
                    <MarkerCategory name="21" DisplayName="#21"/>
                    <MarkerCategory name="22" DisplayName="#22"/>
                    <MarkerCategory name="23" DisplayName="#23"/>
                </MarkerCategory>
                
            </MarkerCategory>
            
            <MarkerCategory name="starlit" DisplayName="Starlit Weald">
                
                <MarkerCategory name="hunt" DisplayName="A Hunt for the Ages" achievementId="8886">
                    <MarkerCategory name="spineshell" DisplayName="Spineshell Impaler" iconFile="Data/Images/Champion Spineshell Impaler.png" mapDisplaySize="64" inGameVisibility="0"/>
                    <MarkerCategory name="emperor" DisplayName="Tyrannus Emperor" iconFile="Data/Images/Elite Tyrannus Emperor.png" mapDisplaySize="64" inGameVisibility="0"/>
                    <MarkerCategory name="man-eater" DisplayName="Tyrannus Man-Eater" iconFile="Data/Images/Champion Tyrannus Man Eater.png" mapDisplaySize="64" inGameVisibility="0"/>
                </MarkerCategory>

                <MarkerCategory name="journey" DisplayName="A Magical Journey" achievementId="9048">
                    <MarkerCategory name="sw" IsSeparator="1" DisplayName="STARLIT WEALD"/>
                    <MarkerCategory name="talk" DisplayName="Talk to Hiberus Mythseeker at the Priory Expedition" iconFile="Data/Images/Icons/Talk.png" minSize="20" maxSize="24" mapDisplaySize="40"/>
                    <MarkerCategory name="trapped" DisplayName="Magic from a Trapped Room" iconFile="Data/Images/Yellow Swirl.png" mapDisplaySize="128" inGameVisibility="0">
                        <MarkerCategory name="orb" DisplayName="Fractured Magical Essence" iconFile="Data/Images/Icons/Orb - White - S.png" mapDisplaySize="32" inGameVisibility="1" minSize="20" maxSize="24" heightOffset="-0.25"/>
                    </MarkerCategory>
                    <MarkerCategory name="spirit" DisplayName="Essence of Seer Spirit" iconFile="Data/Images/Yellow Swirl.png" mapDisplaySize="128" inGameVisibility="0"/>
                    <MarkerCategory name="relics" DisplayName="Fragments of Seer Relics" iconFile="Data/Images/Yellow Swirl.png" mapDisplaySize="128" inGameVisibility="0"/>
                    <MarkerCategory name="flower" DisplayName="Magic from an Ancient Flower" iconFile="Data/Images/Yellow Swirl.png" mapDisplaySize="128" inGameVisibility="0"/>
                    <MarkerCategory name="weapon" DisplayName="Remnants of a Seer Weapon" iconFile="Data/Images/Yellow Swirl.png" mapDisplaySize="128" inGameVisibility="0">
                        <MarkerCategory name="orb" DisplayName="Fractured Magical Essence" iconFile="Data/Images/Icons/Orb - White - S.png" mapDisplaySize="32" inGameVisibility="1" minSize="20" maxSize="24" heightOffset="-0.25"/>
                    </MarkerCategory>
                    <MarkerCategory name="orb" DisplayName="Orb of Skimmer-Collected Magic" iconFile="Data/Images/Yellow Swirl.png" mapDisplaySize="128" inGameVisibility="0"/>
                    <MarkerCategory name="gwyldell" DisplayName="Residue from a Subdued Gwyldell" iconFile="Data/Images/Yellow Swirl.png" mapDisplaySize="128" inGameVisibility="0">
                        <MarkerCategory name="gwyldell" DisplayName="Gwyldell" iconFile="Data/Images/Circlet.png" mapDisplaySize="32" inGameVisibility="0"/>
                    </MarkerCategory>
                    <MarkerCategory name="choya" DisplayName="Memories of Life as a Choya" iconFile="Data/Images/Yellow Swirl.png" mapDisplaySize="128" inGameVisibility="0">
                        <MarkerCategory name="orb" DisplayName="Fractured Magical Essence" iconFile="Data/Images/Icons/Orb - White - S.png" mapDisplaySize="32" inGameVisibility="1" minSize="20" maxSize="24" heightOffset="-0.25"/>
                    </MarkerCategory>
                    <MarkerCategory name="ss" IsSeparator="1" DisplayName="SHIPWRECK STRAND"/>
                    <MarkerCategory name="research" DisplayName="Results of Magical Research" iconFile="Data/Images/Yellow Swirl.png" mapDisplaySize="128" inGameVisibility="0"/>
                    <MarkerCategory name="residue" DisplayName="Carcinized Magical Residue" iconFile="Data/Images/Yellow Swirl.png" mapDisplaySize="128" inGameVisibility="0"/>
                    <MarkerCategory name="checkin" DisplayName="Talk to Hiberus Mythseeker at the Priory Expedition" iconFile="Data/Images/Icons/Blank.png"/>
                    <MarkerCategory name="core" IsSeparator="1" DisplayName="CENTRAL TYRIA"/>
                    <MarkerCategory name="jormag" DisplayName="Remnant of Jormag's Magic (Frostgorge Sound)" iconFile="Data/Images/Icons/Collections.png" mapDisplaySize="48" inGameVisibility="0"/>
                    <MarkerCategory name="kralk" DisplayName="Remnant of Kralkatorrik's Magic (Field of Ruin)" iconFile="Data/Images/Icons/Collections.png" mapDisplaySize="48" inGameVisibility="0"/>
                    <MarkerCategory name="primordus" DisplayName="Remnant of Primordus's Magic (Mount Maelstrom)" iconFile="Data/Images/Icons/Collections.png" mapDisplaySize="48" inGameVisibility="0"/>
                    <MarkerCategory name="zhaitan" DisplayName="Remnant of Zhaitan's Magic (Cursed Shore)" iconFile="Data/Images/Icons/Collections.png" mapDisplaySize="48" inGameVisibility="0"/>
                    <MarkerCategory name="soowon" DisplayName="Remnant of Soo Won's Magic (Mount Maelstrom)" iconFile="Data/Images/Icons/Collections.png" mapDisplaySize="48" inGameVisibility="0"/>
                    <MarkerCategory name="mord" DisplayName="Remnant of Mordremoth's Magic (Brisban WIldlands)" iconFile="Data/Images/Icons/Collections.png" mapDisplaySize="48" inGameVisibility="0"/>
                </MarkerCategory>

                <MarkerCategory name="backdoor" DisplayName="Backdoor Exploit [H]" achievementId="9007" iconFile="Data/Images/Icons/Backdoor Exploit.png" mapDisplaySize="32"/>

                <MarkerCategory name="birdie" DisplayName="Birdie Benefactor Jumping Puzzle" achievementId="9028" fadeNear="1200" fadeFar="2400">
                    <MarkerCategory name="set" IsSeparator="1" DisplayName="SETTINGS"/>
                    <MarkerCategory name="sign" DisplayName="Toggle Sign" iconFile="Data/Images/Jumping Puzzles/Birdie Benefactor.png" miniMapVisibility="1" mapVisibility="1" inGameVisibility="0" mapDisplaySize="96"/>
                    <MarkerCategory name="glider" DisplayName="Toggle Glider" iconFile="Data/Images/Icons/Glider.png" inGameVisibility="1" mapVisibility="0" minSize="12" maxSize="24"/>
                </MarkerCategory>

                <MarkerCategory name="choya" DisplayName="Choya Champion Adventure / Race">
                    <MarkerCategory name="set" IsSeparator="1" DisplayName="SETTINGS"/>
                    <MarkerCategory name="sign" DisplayName="Toggle Sign" iconFile="Data/Images/Adventures/The Great Choya Race.png" miniMapVisibility="1" mapVisibility="1" inGameVisibility="0" mapDisplaySize="96"/>
                </MarkerCategory>

                <MarkerCategory name="language" DisplayName="Choya Language Expert" achievementId="8967" iconFile="Data/Images/Yellow Swirl.png" mapDisplaySize="128" inGameVisibility="0"/>

                <MarkerCategory name="dubious" DisplayName="Dubious Dancing (Reqs: Choya Dance event)" achievementId="9069" iconFile="Data/Images/Emote - Dance.png"/>

                <MarkerCategory name="exit" DisplayName="Dubious Exit [H]" achievementId="8982" iconFile="Data/Images/Icons/Targeted Object.png" minSize="20" maxSize="24" mapDisplaySize="40"/>

                <MarkerCategory name="escape" DisplayName="Escape Artist: Defense Systems" achievementId="8886">
                    <MarkerCategory name="turret" DisplayName="Turret Trap" iconFile="Data/Images/Icons/Orb - Blue.png" mapDisplaySize="32" inGameVisibility="0"/>
                    <MarkerCategory name="progenitor" DisplayName="Illusory Progenitor" iconFile="Data/Images/Icons/Orb - Red.png" mapDisplaySize="32" inGameVisibility="0"/>
                    <MarkerCategory name="spirit" DisplayName="Spirit Link" iconFile="Data/Images/Icons/Orb - Purple.png" mapDisplaySize="32" inGameVisibility="0"/>
                    <MarkerCategory name="cursed" DisplayName="Cursed Artifact" iconFile="Data/Images/Icons/Orb - Yellow.png" mapDisplaySize="32" inGameVisibility="0"/>
                    <MarkerCategory name="grinder" DisplayName="Arcane Grinder" iconFile="Data/Images/Icons/Orb - White.png" mapDisplaySize="32" inGameVisibility="0"/>
                </MarkerCategory>

                <MarkerCategory name="grilling" DisplayName="Grilling Buddies (Reqs: Choya Dance event)" achievementId="9045" iconFile="Data/Images/Grilling Buddies.png"/>

                <MarkerCategory name="gwyl" DisplayName="Gwyl Rings" achievementId="8919" texture="Data/Images/Trails/Dashed Lines - Fine with Shadow.png" animSpeed="0">
                    <MarkerCategory name="set" IsSeparator="1" DisplayName="SETTINGS"/>
                    <MarkerCategory name="start" DisplayName="Toggle Start Marker" iconFile="Data/Images/Icons/Start.png" miniMapVisibility="1" mapVisibility="1" inGameVisibility="0" mapDisplaySize="128"/>
                    <MarkerCategory name="talk" DisplayName="Talk to Astral Ward Researcher Cattra" iconFile="Data/Images/Icons/Talk.png" minSize="20" maxSize="24" mapDisplaySize="40"/>
                    <MarkerCategory name="wp" DisplayName="Toggle Waypoint Markers" iconFile="Data/Images/Icons/Blank.png" triggerrange="2" autotrigger="true"/>
                    <MarkerCategory name="numbers" DisplayName="Trail Number">
                        <MarkerCategory name="1" DisplayName="One" iconFile="Data/Images/Numbers/1.png" miniMapVisibility="0" minSize="16" maxSize="24"/>
                        <MarkerCategory name="2" DisplayName="Two" iconFile="Data/Images/Numbers/2.png" miniMapVisibility="0" minSize="16" maxSize="24"/>
                        <MarkerCategory name="3" DisplayName="Three" iconFile="Data/Images/Numbers/3.png" miniMapVisibility="0" minSize="16" maxSize="24"/>
                        <MarkerCategory name="4" DisplayName="Four" iconFile="Data/Images/Numbers/4.png" miniMapVisibility="0" minSize="16" maxSize="24"/>
                        <MarkerCategory name="5" DisplayName="Five" iconFile="Data/Images/Numbers/5.png" miniMapVisibility="0" minSize="16" maxSize="24"/>
                        <MarkerCategory name="6" DisplayName="Six" iconFile="Data/Images/Numbers/6.png" miniMapVisibility="0" minSize="16" maxSize="24"/>
                        <MarkerCategory name="7" DisplayName="Seven" iconFile="Data/Images/Numbers/7.png" miniMapVisibility="0" minSize="16" maxSize="24"/>
                        <MarkerCategory name="8" DisplayName="Eight" iconFile="Data/Images/Numbers/8.png" miniMapVisibility="0" minSize="16" maxSize="24"/>
                        <MarkerCategory name="9" DisplayName="Nine" iconFile="Data/Images/Numbers/9.png" miniMapVisibility="0" minSize="16" maxSize="24"/>
                    </MarkerCategory>
                    <MarkerCategory name="obj" IsSeparator="1" DisplayName="OBJECTIVES"/>
                    <MarkerCategory name="collectible" IsSeparator="1" DisplayName="COLLECTIBLES"/>
                    <MarkerCategory name="rock" DisplayName="rock gwyl ring"/>
                    <MarkerCategory name="saurian" DisplayName="saurian egg gwyl ring"/>
                    <MarkerCategory name="fern" DisplayName="bright fern gwyl ring"/>
                    <MarkerCategory name="poppy" DisplayName="blue poppy gwyl ring"/>
                    <MarkerCategory name="mushroom" DisplayName="red mushroom gwyl ring"/>
                    <MarkerCategory name="coconut" DisplayName="coconut gwyl ring"/>
                    <MarkerCategory name="frog" DisplayName="frog gwyl ring"/>
                    <MarkerCategory name="butterfly" DisplayName="butterfly gwyl ring"/>
                    <MarkerCategory name="wildflower" DisplayName="wildflower gwyl ring"/>
                </MarkerCategory>

                <MarkerCategory name="huntmaster" DisplayName="Huntmaster of Castora (Reqs: Hunter's Camp Heart)" achievementId="8938" iconFile="Data/Images/Book.png" mapDisplaySize="40" inGameVisibility="0"/>

                <MarkerCategory name="hologram" DisplayName="Inquest Hologram" achievementId="9008" iconFile="Data/Images/Icons/Hexagon - Red.png" mapDisplaySize="64" inGameVisibility="0"/>

                <MarkerCategory name="leyline" DisplayName="Ley Line Adventure">
                    <MarkerCategory name="set" IsSeparator="1" DisplayName="SETTINGS"/>
                    <MarkerCategory name="sign" DisplayName="Toggle Sign" iconFile="Data/Images/Adventures/Ley-Line Rider.png" miniMapVisibility="1" mapVisibility="1" inGameVisibility="0" mapDisplaySize="96"/>
                </MarkerCategory>

                <MarkerCategory name="magic" DisplayName="Meandering Magic">
                    <MarkerCategory name="set" IsSeparator="1" DisplayName="SETTINGS"/>
                    <MarkerCategory name="sign" DisplayName="Toggle Sign" iconFile="Data/Images/Jumping Puzzles/Meandering Magic.png" miniMapVisibility="1" mapVisibility="1" inGameVisibility="0" mapDisplaySize="96"/>
                    <MarkerCategory name="location" DisplayName="MAP ZONE" IsSeparator="1"/>
                    <MarkerCategory name="sw" DisplayName="Starlit Weald"/>
                </MarkerCategory>

                <MarkerCategory name="old" DisplayName="Old Magic Adventure" achievementId="9018" texture="Data/Images/Trails/Line - Medium Wide with Shadow.png" animSpeed="0">
                    <MarkerCategory name="set" IsSeparator="1" DisplayName="SETTINGS"/>
                    <MarkerCategory name="sign" DisplayName="Toggle Sign" iconFile="Data/Images/Adventures/Old Magic.png" miniMapVisibility="1" mapVisibility="1" inGameVisibility="0" mapDisplaySize="96"/>
                    <MarkerCategory name="mount" DisplayName="Mounts" miniMapVisibility="0" minSize="24" maxSize="32">
                        <MarkerCategory name="skyscale" DisplayName="Skyscale" iconFile="Data/Images/Mounts/Mount_Skyscale.png"/>
                    </MarkerCategory>
                </MarkerCategory>

                <MarkerCategory name="spelunker" DisplayName="Secret Spelunker" achievementId="8918" animSpeed="0">
                    <MarkerCategory name="hidden" DisplayName="Hidden Aquifer"/>
                    <MarkerCategory name="lost" DisplayName="Lost Grotto"/>
                    <MarkerCategory name="sanctum" DisplayName="Sparkling Sanctum"/>
                </MarkerCategory>

                <MarkerCategory name="history" DisplayName="Shattered History" achievementId="8907" iconFile="Data/Images/Icons/Stone Tablet Fragment.png" mapDisplaySize="40" inGameVisibility="0"/>

                <MarkerCategory name="sketch" DisplayName="Sketch Artist" achievementId="8881" iconFile="Data/Images/Circlet.png" mapDisplaySize="40" inGameVisibility="0"/>

                <MarkerCategory name="soup" DisplayName="Soup's On" achievementId="9033">
                    <MarkerCategory name="set" IsSeparator="1" DisplayName="SETTINGS"/>
                    <MarkerCategory name="talk" DisplayName="Talk to Kjartan the Cook in Hunter's Camp" iconFile="Data/Images/Icons/Talk.png" minSize="20" maxSize="24" mapDisplaySize="40"/>
                </MarkerCategory>

                <MarkerCategory name="bodyguard" DisplayName="Project Bodyguard (EVENT: FRU1TPUNCH)" achievementId="9077" iconFile="Data/Images/Yellow Swirl.png" mapDisplaySize="128" inGameVisibility="0"/>

                <MarkerCategory name="rampage" DisplayName="Rampage Router" achievementId="8902">
                    <MarkerCategory name="event" DisplayName="EVENT: Defend the camp from the wildlife attack" iconFile="Data/Images/Yellow Swirl.png" mapDisplaySize="128" inGameVisibility="0"/>
                    <MarkerCategory name="champion" DisplayName="Champion Tyrannus Man Eater" iconFile="Data/Images/Champion Tyrannus Man Eater.png" mapDisplaySize="48" inGameVisibility="0"/>
                </MarkerCategory>

                <MarkerCategory name="tread" DisplayName="Tread Lightly [H]" achievementId="8941" iconFile="Data/Images/Icons/Gwyllian.png" mapDisplaySize="48" inGameVisibility="0"/>

                <MarkerCategory name="treasures" DisplayName="Treasures of the Last Vault" achievementId="8996" iconFile="Data/Images/Icons/Orb - Yellow.png" minSize="12" maxSize="12" mapDisplaySize="24" heightOffset="-0.25"/>

                <MarkerCategory name="delivery" DisplayName="Wavehawk Delivery" achievementId="8920" iconFile="Data/Images/Yellow Swirl.png" mapDisplaySize="128" inGameVisibility="0"/>

                <MarkerCategory name="savior" DisplayName="Wavehawk Savior" achievementId="8856" iconFile="Data/Images/Yellow Swirl.png" mapDisplaySize="128" inGameVisibility="0">
                    <MarkerCategory name="trap" DisplayName="Wavehawk Trap" iconFile="Data/Images/Circle - Red.png" mapDisplaySize="40" inGameVisibility="0"/>
                </MarkerCategory>

            </MarkerCategory>

            <MarkerCategory name="eternity" DisplayName="Eternity's Garden">
                <MarkerCategory name="reprieve" DisplayName="A Brief Reprieve" achievementId="9314" iconFile="Data/Images/Icons/Orb - Purple - S.png" minSize="20" maxSize="24">
                    <MarkerCategory name="isgarren" DisplayName="Isgarren" iconFile="Data/Images/Icons/IsGarren.png" mapDisplaySize="64" inGameVisibility="0"/>
                </MarkerCategory>
                <MarkerCategory name="calamity" DisplayName="A Crustacean Calamity" achievementId="9297" iconFile="Data/Images/Icons/Talk.png" minSize="20" maxSize="24">
                    <MarkerCategory name="icon" DisplayName="Icon" iconFile="Data/Images/Icons/Crab.png" mapDisplaySize="48" inGameVisibility="0"/>
                </MarkerCategory>
                
                <MarkerCategory name="enquiry" DisplayName="An Imperial Inquiry" achievementId="9250" iconFile="Data/Images/Icons/Collection.png" minSize="24" maxSize="24" mapDisplaySize="48">
                 <MarkerCategory name="collect" DisplayName="Collectible" iconFile="Data/Images/Icons/Collections - Green.png" inGameVisibility="0"/>
                </MarkerCategory>
                
                <MarkerCategory name="arcane" DisplayName="Arcane Certification" achievementId="9281" iconFile="Data/Images/Yellow Swirl.png" mapDisplaySize="128" inGameVisibility="0"/>
                
                <MarkerCategory name="preservation" DisplayName="Arcane Preservation" achievementId="9273" iconFile="Data/Images/Icons/Talk.png" minSize="20" maxSize="24">
                    <MarkerCategory name="event" DisplayName="EVENT: Help Steward Cecco unfuse animals of their seer influence" iconFile="Data/Images/Yellow Swirl.png" mapDisplaySize="128" inGameVisibility="0" tip-name="EVENT: Help Steward Cecco unfuse animals of their seer influence"/>
                </MarkerCategory>                    
                
                <MarkerCategory name="arjp" DisplayName="Artificer's Rise Jumping Puzzle" achievementId="9290" iconFile="Data/Images/Icons/talk.png" minSize="20" maxSize="24" fadeNear="900" fadeFar="1200">
                    <MarkerCategory name="glider" DisplayName="Glider" iconFile="Data/Images/Icons/Glider.png" minSize="16" maxSize="24" mapVisibility="0" fadeNear="900" fadeFar="1200"/>
                    <MarkerCategory name="sign" DisplayName="Sign" iconFile="Data/Images/Jumping Puzzles/Artificer's Rise.png" mapDisplaySize="128" inGameVisibility="0"/>
                </MarkerCategory>

                <MarkerCategory name="audience" DisplayName="Attentive Audience" achievementId="9302" iconFile="Data/Images/Icons/Talk.png" minSize="20" maxSize="24">
                    <MarkerCategory name="icon" DisplayName="PTM" iconFile="Data/Images/Icons/PTM.png" mapDisplaySize="64" inGameVisibility="0"/>
                </MarkerCategory>

                <MarkerCategory name="beetle" DisplayName="Beetle Research" achievementId="9277" iconFile="Data/Images/Icons/Beetle Specimen.png" mapDisplaySize="32" inGameVisibility="0"/>
                
                <MarkerCategory name="calculated" DisplayName="Calculated Destruction" achievementId="9325" iconFile="Data/Images/Yellow Swirl.png" mapDisplaySize="128" inGameVisibility="0"/>
                
                <MarkerCategory name="cursebreaker" DisplayName="Castoran Curse Breaker" achievementId="9253" iconFile="Data/Images/Icons/Orb - Blue.png" maxSize="16" heightOffset="-0.5"/>
                
                <MarkerCategory name="overgrowth" DisplayName="Castoran Overgrowth" achievementId="9298" iconFile="Data/Images/Yellow Swirl.png" mapDisplaySize="128" inGameVisibility="0"/>
                
                <MarkerCategory name="cruel" DisplayName="Cruel Creations" achievementId="9296" iconFile="Data/Images/Yellow Swirl.png" mapDisplaySize="128" inGameVisibility="0"/>
                

                <MarkerCategory name="divine" DisplayName="Divine Historian" achievementId="9338" iconFile="Data/Images/Yellow Swirl.png" mapDisplaySize="128" inGameVisibility="0"/>
                
                <MarkerCategory name="gregorios" DisplayName="Gregorios the Beautiful" achievementId="9294" iconFile="Data/Images/Icons/Hullgardener Gregorious.png" minSize="20" maxSize="24" mapDisplaySize="48">
                    <MarkerCategory name="flower" DisplayName="Most Beautiful Flower" iconFile="Data/Images/Icons/Red Iris Flower.png" mapDisplaySize="40" inGameVisibility="0"/>
                    <MarkerCategory name="talk" DisplayName="Talk to Hullgardener Gregorious" iconFile="Data/Images/Icons/Talk.png" minSize="20" maxSize="24"/>
                </MarkerCategory>
                
                <MarkerCategory name="kitshark" DisplayName="Kitshark Fishing" achievementId="9311" iconFile="Data/Images/Icons/Talk.png" minSize="20" maxSize="24"/>
                
                <MarkerCategory name="entertainment" DisplayName="Kitshark Entertainment" achievementId="9258" iconFile="Data/Images/Icons/Kitshark.png" minSize="20" maxSize="24" mapDisplaySize="48" inGameVisibility="0"/>
        

                <MarkerCategory name="translation" DisplayName="Lost in Translation" achievementId="9295" iconFile="Data/Images/Icons/Orb - Blue.png" minSize="20" maxSize="24" mapDisplaySize="32"/>

                <MarkerCategory name="master" DisplayName="Master of Sacred Arms" achievementId="9248" iconFile="Data/Images/Icons/Talk.png" minSize="20" maxSize="24">
                    <MarkerCategory name="event" DisplayName="EVENT: Thrumming Faceted Shadowstone" iconFile="Data/Images/Icons/Master of Sacred Arms.png" mapDisplaySize="48" inGameVisibility="0" tip-name="EVENT: Help Steward Cecco unfuse animals of their seer influence"/>
                </MarkerCategory>
                <MarkerCategory name="moth" DisplayName="Moth Enthusiast [H]" achievementId="9337" iconFile="Data/Images/Icons/Moth.png" mapDisplaySize="48" inGameVisibility="0"/>
                <MarkerCategory name="alone" DisplayName="No Longer Alone [H]" achievementId="9255" iconFile="Data/Images/Emote - Cheer.png" inGameVisibility="1"/>

                <MarkerCategory name="otter" DisplayName="Otter Snack Time [H]" achievementId="9249" iconFile="Data/Images/Icons/Fish.png" minSize="20" maxSize="24" mapVisibility="0"/>

                <MarkerCategory name="potd" DisplayName="Path of the Divine" achievementId="9304" iconFile="Data/Images/Icons/Historian Minna.png" minSize="20" maxSize="24" mapDisplaySize="48"/>

                <MarkerCategory name="mothmarsh" DisplayName="Protector of the Mothmarsh" achievementId="9322" iconFile="Data/Images/Icons/Giant Beetle.png" mapDisplaySize="48" inGameVisibility="0" tip-name="EVENT: Defend the cocoons from beetles"/>

                <MarkerCategory name="questionable" DisplayName="Questionable Choices" achievementId="9341" iconFile="Data/Images/Icons/Shadowstone.png" mapDisplaySize="48" inGameVisibility="0" tip-name="Questionable Choices"/>
                <!--
                <MarkerCategory name="ancients" DisplayName="Respect for the Ancients" achievementId="9257" iconFile="Data/Images/Icons/Leywright Edifi.png" tip-name="EVENT: Explore the temple with Historian Minna" mapDisplaySize="48" inGameVisibility="0"/>
                -->
                <MarkerCategory name="forge" DisplayName="Revitalizing the Forge" achievementId="9306" iconFile="Data/Images/Icons/Leywright Edifi.png" tip-name="EVENT: Help Steward Edifi build more stewards" mapDisplaySize="48" inGameVisibility="0"/>
                <MarkerCategory name="risky" DisplayName="Risky Research" achievementId="9315" iconFile="Data/Images/Icons/Lutorius Tomeweaver.png" minSize="20" maxSize="24" mapDisplaySize="48"/>
                
                <MarkerCategory name="sacking" DisplayName="Sacking the Inquest" achievementId="9309" iconFile="Data/Images/Icons/Inquest Cache.png" mapDisplaySize="48" inGameVisibility="0" tip-name="Inquest Cache"/>
                <MarkerCategory name="savior" DisplayName="Savior of the Gwyldell" achievementId="9242">
                    <MarkerCategory name="research" DisplayName="Research Notes" iconFile="Data/Images/Icons/Inquest Research Notes.png" mapDisplaySize="40" inGameVisibility="0"/>
                </MarkerCategory>
                <MarkerCategory name="scholar" DisplayName="Scholar of the Garden" achievementId="9321" iconFile="Data/Images/Icons/Book - Green.png" minSize="20" maxSize="24" mapDisplaySize="48"/>
                
                <MarkerCategory name="shepherd" DisplayName="Shepherd of the Garden" achievementId="9324" iconFile="Data/Images/Icons/Spell Guardian.png" mapDisplaySize="48" inGameVisibility="0"/>
                
                <MarkerCategory name="scour" DisplayName="Skimmer Relic Scour" achievementId="9254" inGameVisibility="1"/>
                
                <MarkerCategory name="temple" DisplayName="Temple of Abnegation Jumping Puzzle" achievementId="9327"  fadeNear="1200" fadeFar="1600">
                    <MarkerCategory name="sign" DisplayName="Sign" iconFile="Data/Images/Jumping Puzzles/Temple of Abnegation.png" mapDisplaySize="128" inGameVisibility="0"/>
                </MarkerCategory>

                <MarkerCategory name="hard" DisplayName="The Hard Choice" achievementId="9264" iconFile="Data/Images/Icons/Steward of Galdra.png" tip-name="GROUP EVENT: Defeat the Inquest augmented Steward of Galdra" mapDisplaySize="48" inGameVisibility="0"/>
                <MarkerCategory name="halls" DisplayName="These Cursed Halls" achievementId="9328" iconFile="Data/Images/Icons/Talk.png" minSize="20" maxSize="24">
                    <MarkerCategory name="event" DisplayName="GROUP EVENT: Enter and conquer the Temple of Abnegation" iconFile="Data/Images/Yellow Swirl.png" mapDisplaySize="128" inGameVisibility="0" tip-name="EVENT: Help Steward Cecco unfuse animals of their seer influence"/>
                </MarkerCategory>
                
                <MarkerCategory name="uplift" DisplayName="The Uplift (Req: On the Threshold)" achievementId="9318"  iconFile="Data/Images/Icons/Collection.png" mapDisplaySize="48" inGameVisibility="0">
                    <MarkerCategory name="fragment" DisplayName="Fragment" iconFile="Data/Images/Icons/Collections.png" minSize="20" maxSize="24" fadeNear="2000" fadeFar="2400" mapDisplaySize="40" inGameVisibility="1"/>
                </MarkerCategory>

                <MarkerCategory name="allies" DisplayName="Unexpected Allies" achievementId="9270">
                    <MarkerCategory name="emote" DisplayName="Emote" iconFile="Data/Images/Emote - Any.png" minSize="32" maxSize="32" fadeNear="1200" fadeFar="1600" heightOffset="0.2"/>
                    <MarkerCategory name="gwyllian" DisplayName="Gwyllian" iconFile="Data/Images/Icons/Gwyllian.png" mapDisplaySize="48" inGameVisibility="0"/>
                    <MarkerCategory name="kela" DisplayName="Kela" iconFile="Data/Images/Icons/Kela.png" mapDisplaySize="48" inGameVisibility="0"/>
                </MarkerCategory>
                
                
                
                
            </MarkerCategory>

            
        </MarkerCategory>
            
    </MarkerCategory>
    <!-- End of Lady Elyssa's AP Guides -->
</OverlayData>
